physicstool/__init__.py
physicstool-0.0.0.dist-info/LICENCE
physicstool-0.0.0.dist-info/METADATA
physicstool-0.0.0.dist-info/WHEEL
physicstool-0.0.0.dist-info/top_level.txt
physicstool-0.0.0.dist-info/RECORD
