Metadata-Version: 2.2
Name: physicstool
Version: 0.0.0
Summary: A simple Python package to do basic physics calculations.
Author-email: Marc van der Sluys <git@vandersluys.nl>
License: EUPL 1.2
Project-URL: GitHub, https://github.com/MarcvdSluys/physicstool
Project-URL: ReadTheDocs, https://physicstool.readthedocs.io
Keywords: physics,technology,natural sciences
Classifier: Development Status :: 3 - Alpha
Classifier: Intended Audience :: Developers
Classifier: Intended Audience :: Education
Classifier: Intended Audience :: Science/Research
Classifier: License :: OSI Approved :: European Union Public Licence 1.2 (EUPL 1.2)
Classifier: Natural Language :: English
Classifier: Operating System :: OS Independent
Classifier: Programming Language :: Python :: 3
Classifier: Topic :: Scientific/Engineering
Classifier: Topic :: Scientific/Engineering :: Astronomy
Classifier: Topic :: Scientific/Engineering :: Physics
License-File: LICENCE
Requires-Dist: numpy
